iocide/__init__.py
iocide/__main__.py
iocide/blobs.py
iocide/cli.py
iocide/deobfuscate.py
iocide/email.py
iocide/hashes.py
iocide/hostname.py
iocide/inputs.py
iocide/ip.py
iocide/rfc_3548.py
iocide/template.py
iocide/url.py
iocide/data/top_level_domains.txt
iocide-0.2.0.dist-info/LICENSE
iocide-0.2.0.dist-info/METADATA
iocide-0.2.0.dist-info/WHEEL
iocide-0.2.0.dist-info/entry_points.txt
iocide-0.2.0.dist-info/top_level.txt
iocide-0.2.0.dist-info/RECORD
