Metadata-Version: 2.1
Name: iocide
Version: 0.2.0
Summary: Indicator of Compromise (IOC) Detection Utility
Home-page: https://gitlab.com/dsfinn/iocide
Author: David Finn
Author-email: dsfinn@gmail.com
License: UNKNOWN
Platform: UNKNOWN
Classifier: License :: OSI Approved :: GNU General Public License v3 (GPLv3)
Classifier: Programming Language :: Python :: 3.6
Classifier: Topic :: Security
Requires-Python: >=3.6
Requires-Dist: chardet (>=4.0.0)
Requires-Dist: pdfminer.six (>=20201018)
Requires-Dist: regex (>=2021.4.4)
Requires-Dist: unidecode (>=1.2.0)
